setup.py
funniest/__init__.py
funniest/command_line.py
funniest/text.py
funniestlc.egg-info/PKG-INFO
funniestlc.egg-info/SOURCES.txt
funniestlc.egg-info/dependency_links.txt
funniestlc.egg-info/entry_points.txt
funniestlc.egg-info/not-zip-safe
funniestlc.egg-info/requires.txt
funniestlc.egg-info/top_level.txt