Metadata-Version: 1.0
Name: funniestlc
Version: 0.3
Summary: The funniest joke in the world
Home-page: https://bitbucket.org/leechau/pynote
Author: Li Chao
Author-email: leechau@126.com
License: MIT
Platform: UNKNOWN
